extracty/__init__.py
extracty/llm_extractor.py
extracty/scraper.py
extracty-0.1.1.dist-info/METADATA
extracty-0.1.1.dist-info/WHEEL
extracty-0.1.1.dist-info/RECORD
