Metadata-Version: 2.1
Name: extracty
Version: 0.1.1
Summary: extract structured data from any unstructered web page
License: MIT
Author: Mamdouh66
Requires-Python: >=3.11,<4.0
Classifier: License :: OSI Approved :: MIT License
Classifier: Programming Language :: Python :: 3
Classifier: Programming Language :: Python :: 3.11
Classifier: Programming Language :: Python :: 3.12
Requires-Dist: beautifulsoup4 (>=4.12.3,<5.0.0)
Requires-Dist: fake-useragent (>=1.5.1,<2.0.0)
Requires-Dist: instructor (>=0.6.7,<0.7.0)
Requires-Dist: langchain-community (>=0.0.29,<0.0.30)
Requires-Dist: openai (>=1.14.3,<2.0.0)
Requires-Dist: playwright (>=1.42.0,<2.0.0)
Requires-Dist: pydantic (>=2.6.4,<3.0.0)
